omnifold/__init__.py
omnifold/dataloader.py
omnifold/net.py
omnifold/omnifold.py
omnifold/utils.py
omnifold-0.1.36.dist-info/METADATA
omnifold-0.1.36.dist-info/WHEEL
omnifold-0.1.36.dist-info/top_level.txt
omnifold-0.1.36.dist-info/RECORD
